pubmed_temporal/__init__.py
pubmed_temporal/data.py
pubmed_temporal/graph.py
pubmed_temporal/planetoid.py
pubmed_temporal-1.1.1.dist-info/METADATA
pubmed_temporal-1.1.1.dist-info/WHEEL
pubmed_temporal-1.1.1.dist-info/top_level.txt
pubmed_temporal-1.1.1.dist-info/RECORD
