Metadata-Version: 2.4
Name: pubmed-temporal
Version: 1.1.1
Summary: Build PubMed temporal graph dataset using data from the PubMed API.
Author-email: Nelson Aloysio Reis de Almeida Passos <nelson.reis@phd.unipi.it>
Project-URL: Homepage, https://pypi.org/p/pubmed-temporal/
Project-URL: Repository, https://github.com/nelsonaloysio/pubmed-temporal
Project-URL: Issues, https://github.com/nelsonaloysio/pubmed-temporal/issues
Project-URL: Changelog, https://github.com/nelsonaloysio/pubmed-temporal/blob/main/CHANGELOG.md
Keywords: Network,Graph,Dynamic Graph,Temporal Network
Classifier: Development Status :: 5 - Production/Stable
Classifier: Intended Audience :: Developers
Classifier: Intended Audience :: Information Technology
Classifier: Intended Audience :: Science/Research
Classifier: License :: OSI Approved :: MIT License
Classifier: Programming Language :: Python :: 3
Classifier: Topic :: Scientific/Engineering :: Information Analysis
Classifier: Topic :: Software Development :: Libraries :: Python Modules
Requires-Python: >=3.7
Requires-Dist: networkx>=2.1
Requires-Dist: pandas>=2.0.3
Requires-Dist: pubmed-id>=1.0
Requires-Dist: torch_geometric>=2.4.0
Provides-Extra: extra
Requires-Dist: matplotlib>=3.8.2; extra == "extra"
Requires-Dist: tabulate>=0.9.0; extra == "extra"
